qlazy/Backend.py
qlazy/CMem.py
qlazy/DensOp.py
qlazy/MData.py
qlazy/MPState.py
qlazy/Observable.py
qlazy/ObservableBase.py
qlazy/PauliProduct.py
qlazy/QCirc.py
qlazy/QObject.py
qlazy/QState.py
qlazy/Result.py
qlazy/Stabilizer.py
qlazy/__init__.py
qlazy/config.py
qlazy/core.py
qlazy/error.py
qlazy/gpu.py
qlazy/qlazy
qlazy/util.py
qlazy/backend/__init__.py
qlazy/backend/amazon_braket.py
qlazy/backend/ibmq.py
qlazy/backend/qlazy_mps_simulator.py
qlazy/backend/qlazy_qstate_simulator.py
qlazy/backend/qlazy_stabilizer_simulator.py
qlazy/backend/qulacs_simulator.py
qlazy/lib/__init__.py
qlazy/lib/cmem_c.py
qlazy/lib/densop_c.py
qlazy/lib/densop_func.py
qlazy/lib/gpu_c.py
qlazy/lib/libqlz.so
qlazy/lib/mdata_c.py
qlazy/lib/mpstate_func.py
qlazy/lib/observable_base_c.py
qlazy/lib/qcirc_c.py
qlazy/lib/qstate_c.py
qlazy/lib/stabilizer_c.py
qlazy/lib/c/Makefile
qlazy/lib/c/cmem.c
qlazy/lib/c/densop.c
qlazy/lib/c/gbank.c
qlazy/lib/c/gpu.cu
qlazy/lib/c/help.c
qlazy/lib/c/mdata.c
qlazy/lib/c/message.c
qlazy/lib/c/misc.c
qlazy/lib/c/observable_base.c
qlazy/lib/c/qc.c
qlazy/lib/c/qcirc.c
qlazy/lib/c/qg.c
qlazy/lib/c/qgate.c
qlazy/lib/c/qlazy.c
qlazy/lib/c/qlazy.h
qlazy/lib/c/qstate.c
qlazy/lib/c/qstate_gpu.cu
qlazy/lib/c/qsystem.c
qlazy/lib/c/random.c
qlazy/lib/c/spro.c
qlazy/lib/c/stabilizer.c
qlazy/lib/c/tagtable.c
qlazy/lib/c/version.h
qlazy/tools/Probability.py
qlazy/tools/Register.py
qlazy/tools/__init__.py
qlazy-0.3.4.dist-info/LICENSE
qlazy-0.3.4.dist-info/METADATA
qlazy-0.3.4.dist-info/WHEEL
qlazy-0.3.4.dist-info/entry_points.txt
qlazy-0.3.4.dist-info/top_level.txt
qlazy-0.3.4.dist-info/RECORD
