Metadata-Version: 2.1
Name: qlazy
Version: 0.3.4
Summary: Quantum Computing Simulator
Home-page: https://github.com/samn33/qlazy
Author: Sam.N
Author-email: saminriver33@gmail.com
License: Apache Software License
Keywords: quantum,simulator
Classifier: Development Status :: 4 - Beta
Classifier: Programming Language :: Python
Classifier: License :: OSI Approved :: Apache Software License
License-File: LICENSE
Requires-Dist: numpy (>=1.21.0)
Requires-Dist: tensornetwork (>=0.4.6)
